{
  "family": "RSC85",
  "normalized_from_xsc": false,
  "magic_hex": "52 53 43 85",
  "resource_type": 2,
  "flag1": 2147483648,
  "flag2": 2147483667,
  "header_size": 16,
  "stored_size": 30238,
  "payload_size": 30222,
  "expected_unpacked_size": 77824,
  "compression": "zstandard",
  "encryption": "aes-256-ecb-16-pass",
  "path": "D:\\Games\\Red Dead Redemption\\Code_RED\\build\\mp_xenon_full_conversion_pass2\\all_converted_editable_wsc\\_hash_named_extensionless_editable\\playground\\0x50C0D3DF.wsc",
  "source_sha256": "91CB6B016B5C576E4B8364C7B2A55250318D217B5AD613A54B5AB5C2ACC7885D",
  "normalized_sha256": "91CB6B016B5C576E4B8364C7B2A55250318D217B5AD613A54B5AB5C2ACC7885D",
  "decoded_sha256": "5678B242FA95BC688165BF1EA3F1F8D42B752B49723C7E90DDBD69A81B14A945",
  "decoded_size": 77824,
  "key_attempts": [
    {
      "method": "rdr_exe",
      "path": "D:\\Games\\Red Dead Redemption\\RDR.exe",
      "exists": true,
      "offset": "0x2293500",
      "key_sha1": "87862497EE46855372B51C7A324A2BB5CD66F4AF"
    }
  ],
  "decode_error": ""
}